mabini/__init__.py
make_test009-0.0.1.dist-info/METADATA
make_test009-0.0.1.dist-info/WHEEL
make_test009-0.0.1.dist-info/top_level.txt
make_test009-0.0.1.dist-info/RECORD
